{
  "990": "São Paulo",
  "710": "São Paulo",
  "709": "Santa Albertina",
  "706": "Bernardino de Campos",
  "708": "Santa Salete",
  "707": "Pindorama",
  "705": "Aspásia",
  "704": "São Paulo",
  "703": "São Paulo",
  "702": "São Paulo",
  "701": "Ibitinga",
  "700": "Olímpia",
  "699": "Sorocaba",
  "697": "Jales",
  "698": "Monte Alto",
  "696": "Fernandópolis",
  "695": "Atibaia",
  "694": "Piracaia",
  "693": "Tatuí",
  "692": "Ribeirão Bonito",
  "691": "Itapeva",
  "690": "Votuporanga",
  "689": "Santa Fé do Sul",
  "687": "Pereira Barreto",
  "688": "Assis",
  "686": "Cachoeira Paulista",
  "685": "Itapecerica da Serra",
  "684": "Bananal",
  "683": "Paulo de Faria",
  "682": "Monte Aprazível",
  "680": "Itapecerica da Serra",
  "681": "Vinhedo",
  "679": "Jundiaí",
  "678": "Barra Bonita",
  "677": "Ibitinga",
  "676": "Mirandópolis",
  "675": "São José do Rio Preto",
  "674": "Assis",
  "673": "Adamantina",
  "672": "Tatuí",
  "671": "Olímpia",
  "670": "Jacupiranga",
  "669": "Porangaba",
  "666": "Mogi-Mirim",
  "668": "Sertãozinho",
  "667": "Jacupiranga",
  "665": "Presidente Prudente",
  "664": "Votuporanga",
  "663": "Votorantim",
  "660": "Viradouro",
  "659": "Vinhedo",
  "655": "Várzea Paulista",
  "654": "Cotia",
  "653": "Vargem Grande do Sul",
  "651": "Valparaíso",
  "650": "Valinhos",
  "648": "Urupês",
  "646": "Urânia",
  "642": "Ubatuba",
  "638": "Tupi Paulista",
  "637": "Tupã",
  "634": "Tremembé",
  "629": "Tietê",
  "627": "Teodoro Sampaio",
  "625": "Taubaté",
  "624": "Tatuí",
  "620": "Taquarituba",
  "619": "Taquaritinga",
  "614": "Tambaú",
  "615": "Tanabi",
  "609": "Taboão da Serra",
  "607": "Catanduva",
  "606": "Suzano",
  "604": "Sumaré",
  "602": "Sorocaba",
  "601": "Socorro",
  "597": "Sertãozinho",
  "582": "São Miguel Arcanjo",
  "596": "Serrana",
  "595": "Serra Negra",
  "590": "São Vicente",
  "589": "São Simão",
  "588": "São José do Rio Pardo",
  "587": "São Sebastião",
  "586": "São Roque",
  "584": "São Pedro",
  "581": "São Manuel",
  "579": "São Luiz do Paraitinga",
  "577": "São José dos Campos",
  "575": "São José do Rio Pardo",
  "576": "São José do Rio Preto",
  "572": "São Joaquim da Barra",
  "568": "São João da Boa Vista",
  "566": "São Carlos",
  "565": "São Caetano do Sul",
  "563": "São Bento do Sapucaí",
  "564": "São Bernardo do Campo",
  "562": "Santos",
  "554": "Santo André",
  "553": "Santo Anastácio",
  "549": "Santa Rosa de Viterbo",
  "547": "Santa Rita do Passa Quatro",
  "543": "Santa Isabel",
  "541": "Santa Fé do Sul",
  "539": "Santa Cruz do Rio Pardo",
  "538": "Santa Cruz das Palmeiras",
  "534": "Santa Branca",
  "533": "Santa Bárbara D'Oeste",
  "531": "Santa Adélia",
  "526": "Salto",
  "523": "Santa Branca",
  "516": "Aparecida",
  "515": "Rosana",
  "512": "Ribeirão Pires",
  "511": "Piracicaba",
  "510": "Rio Claro",
  "506": "Ribeirão Preto",
  "505": "Ribeirão Pires",
  "498": "Ribeirão Bonito",
  "493": "Regente Feijó",
  "495": "Registro",
  "491": "Rancharia",
  "488": "Queluz",
  "486": "Quatá",
  "484": "Promissão",
  "483": "Presidente Venceslau",
  "482": "Presidente Prudente",
  "481": "Presidente Epitácio",
  "480": "Presidente Bernardes",
  "477": "Praia Grande",
  "474": "Potirendaba",
  "472": "Porto Ferreira",
  "471": "Porto Feliz",
  "470": "Porangaba",
  "466": "Pontal",
  "464": "Pompéia",
  "462": "Poá",
  "459": "Pitangueiras",
  "458": "Piratininga",
  "457": "Pirassununga",
  "456": "Pirapozinho",
  "453": "Pirajuí",
  "452": "Piraju",
  "451": "Piracicaba",
  "450": "Piracaia",
  "449": "Lorena",
  "447": "Bragança Paulista",
  "445": "Pindamonhangaba",
  "444": "Pilar do Sul",
  "441": "Peruíbe",
  "443": "Piedade",
  "439": "Pereira Barreto",
  "438": "Penápolis",
  "435": "Pedreira",
  "434": "Pedregulho",
  "431": "Pederneiras",
  "430": "Paulo de Faria",
  "428": "Campinas",
  "426": "Patrocínio Paulista",
  "424": "Jacupiranga",
  "420": "Avaré",
  "418": "Paraibuna",
  "417": "Paraguaçu Paulista",
  "416": "Panorama",
  "415": "Palmital",
  "414": "Palmeira D'Oeste",
  "412": "Palestina",
  "411": "Pacaembu",
  "408": "Ourinhos",
  "407": "Osvaldo Cruz",
  "400": "Olímpia",
  "405": "Osasco",
  "404": "Orlândia",
  "397": "Nuporanga",
  "396": "Novo Horizonte",
  "394": "Nova Odessa",
  "390": "Nova Granada",
  "383": "Nhandeara",
  "382": "Mirassol",
  "374": "Morro Agudo",
  "372": "Monte Mor",
  "370": "Monte Azul Paulista",
  "369": "Monte Aprazível",
  "368": "Monte Alto",
  "366": "Mongaguá",
  "363": "Mogi-Mirim",
  "362": "Mogi-Guaçu",
  "361": "Mogi das Cruzes",
  "360": "Mococa",
  "358": "Mirassol",
  "357": "Mirante do Paranapanema",
  "356": "Mirandópolis",
  "355": "Miracatu",
  "352": "Miguelópolis",
  "348": "Mauá",
  "347": "Matão",
  "344": "Marília",
  "346": "Martinópolis",
  "341": "Maracaí",
  "338": "Mairiporã",
  "337": "Mairinque",
  "334": "Monte Aprazível",
  "333": "Macatuba",
  "320": "Limeira",
  "326": "Lucélia",
  "323": "Lorena",
  "322": "Lins",
  "319": "Lençóis Paulista",
  "318": "Leme",
  "315": "Laranjal Paulista",
  "312": "Juquiá",
  "311": "Junqueirópolis",
  "309": "Jundiaí",
  "306": "José Bonifácio",
  "302": "Jaú",
  "301": "Atibaia",
  "300": "Jardinópolis",
  "299": "Barueri",
  "296": "Jaguariúna",
  "297": "Jales",
  "294": "Jacupiranga",
  "292": "Jacareí",
  "291": "Jaboticabal",
  "288": "Ituverava",
  "286": "Itu",
  "283": "Rio Claro",
  "282": "Botucatu",
  "281": "Itatiba",
  "280": "Itanhaém",
  "278": "Itaquaquecetuba",
  "279": "Itararé",
  "274": "Itápolis",
  "275": "Itaporanga",
  "272": "Itapira",
  "271": "Itapevi",
  "270": "Itapeva",
  "269": "Itapetininga",
  "268": "Itapecerica da Serra",
  "266": "Itanhaém",
  "264": "Novo Horizonte",
  "257": "Ipuã",
  "263": "Itaí",
  "262": "Itapeva",
  "247": "São Sebastião",
  "252": "Ipauçu",
  "248": "Indaiatuba",
  "246": "Ilha Solteira",
  "244": "Iguape",
  "242": "Igarapava",
  "240": "Rancharia",
  "238": "Ibiúna",
  "236": "Ibitinga",
  "233": "São Carlos",
  "229": "Sumaré",
  "224": "Guarulhos",
  "200": "Gália",
  "223": "Guarujá",
  "222": "Guariba",
  "220": "Guaratinguetá",
  "219": "Mogi das Cruzes",
  "213": "Guará",
  "218": "Guararapes",
  "210": "Guaíra",
  "205": "Getulina",
  "204": "General Salgado",
  "201": "Garça",
  "197": "Francisco Morato",
  "198": "Franco da Rocha",
  "196": "Franca",
  "191": "Poá",
  "189": "Fernandópolis",
  "187": "Fartura",
  "185": "Estrela D'Oeste",
  "180": "Espírito Santo do Pinhal",
  "177": "Itapecerica da Serra",
  "176": "Embu",
  "172": "Eldorado",
  "169": "Duartina",
  "168": "Dracena",
  "165": "Dois Córregos",
  "161": "Diadema",
  "159": "Cunha",
  "160": "Descalvado",
  "152": "Cotia",
  "157": "Cubatão",
  "156": "Cruzeiro",
  "153": "Cravinhos",
  "150": "Cosmópolis",
  "146": "Cordeirópolis",
  "145": "Conchas",
  "144": "Mogi-Mirim",
  "142": "Colina",
  "140": "Chavantes",
  "136": "Cerqueira César",
  "137": "Cerquilho",
  "132": "Catanduva",
  "129": "Casa Branca",
  "127": "Carapicuíba",
  "128": "Cardoso",
  "125": "Capivari",
  "126": "Caraguatatuba",
  "123": "Capão Bonito",
  "120": "Cândido Mota",
  "118": "Cananéia",
  "116": "Campos do Jordão",
  "115": "Jundiaí",
  "114": "Campinas",
  "111": "Cajuru",
  "108": "Jundiaí",
  "106": "Franco da Rocha",
  "104": "Cafelândia",
  "103": "Caconde",
  "102": "Cachoeira Paulista",
  "101": "Caçapava",
  "100": "São Paulo",
  "99": "Bragança Paulista",
  "97": "Buritama",
  "95": "Brotas",
  "94": "Brodowski",
  "93": "Guarujá",
  "91": "Mogi das Cruzes",
  "90": "São Paulo",
  "88": "São Paulo",
  "89": "São Paulo",
  "86": "São Paulo",
  "87": "São Paulo",
  "84": "Campinas",
  "85": "São Paulo",
  "83": "Aguaí",
  "82": "Boituva",
  "81": "Adamantina",
  "80": "Cabreúva",
  "79": "Botucatu",
  "77": "Birigüi",
  "76": "Bilac",
  "73": "Avaré",
  "75": "Santos",
  "72": "Bebedouro",
  "71": "Bauru",
  "70": "Batatais",
  "69": "Tupã",
  "68": "Barueri",
  "67": "Borborema",
  "66": "Barretos",
  "63": "Barra Bonita",
  "62": "Bariri",
  "60": "Auriflama",
  "59": "Bananal",
  "58": "Agudos",
  "53": "São Paulo",
  "52": "São Paulo",
  "50": "São Paulo",
  "48": "Atibaia",
  "47": "Assis",
  "45": "Santa Isabel",
  "42": "Altinópolis",
  "40": "Araraquara",
  "38": "Araras",
  "37": "Araraquara",
  "35": "Águas de Lindóia",
  "32": "Araçatuba",
  "28": "Aparecida",
  "24": "Andradina",
  "25": "Angatuba",
  "30": "Apiaí",
  "22": "Amparo",
  "21": "São Paulo",
  "20": "São Paulo",
  "17": "São Paulo",
  "19": "Americana",
  "18": "São Paulo",
  "16": "São Paulo",
  "15": "São Paulo",
  "14": "São Paulo",
  "13": "São Paulo",
  "12": "São Paulo",
  "11": "São Paulo",
  "10": "São Paulo",
  "9": "São Paulo",
  "8": "São Paulo",
  "7": "São Paulo",
  "6": "São Paulo",
  "5": "São Paulo",
  "4": "São Paulo",
  "3": "São Paulo",
  "2": "São Paulo",
  "1": "São Paulo",
  "0": "São Paulo"
}
